README.md
setup.py
pyparsers/__init__.py
pyparsers.egg-info/PKG-INFO
pyparsers.egg-info/SOURCES.txt
pyparsers.egg-info/dependency_links.txt
pyparsers.egg-info/requires.txt
pyparsers.egg-info/top_level.txt
pyparsers/CYK/Field.py
pyparsers/CYK/NotParsedException.py
pyparsers/CYK/PlaceItem.py
pyparsers/CYK/__init__.py
pyparsers/CYK/cyk.py