Metadata-Version: 2.1
Name: pyparsers
Version: 0.0.3
Summary: Parsers for grammpy library
Home-page: https://github.com/PatrikValkovic/pyparsers
Author: Patrik Valkovic
Author-email: patrik.valkovic@hotmail.cz
License: GNU General Public License v3.0
Download-URL: https://github.com/PatrikValkovic/pyparsers/archive/v0.0.3.tar.gz
Platform: UNKNOWN
